MANIFEST.in
README.md
setup.cfg
setup.py
PyWapFetion/AliveKeeper.py
PyWapFetion/Cache.py
PyWapFetion/Errors.py
PyWapFetion/Fetion.py
PyWapFetion/__init__.py
PyWapFetion.egg-info/PKG-INFO
PyWapFetion.egg-info/SOURCES.txt
PyWapFetion.egg-info/dependency_links.txt
PyWapFetion.egg-info/not-zip-safe
PyWapFetion.egg-info/top_level.txt